flask_google_signin/__init__.py
flask_google_signin-0.0.7.dist-info/LICENSE
flask_google_signin-0.0.7.dist-info/METADATA
flask_google_signin-0.0.7.dist-info/WHEEL
flask_google_signin-0.0.7.dist-info/top_level.txt
flask_google_signin-0.0.7.dist-info/RECORD
